{"lastUsed":1676880917063,"path":"C:\/Work\/java_work","projectCount":1,"recentFiles":[{"path":"\/Java\/src\/basic","parentWorkspace":"C:\/Work\/java_work","name":"BooleanExample.java","lastModified":1676857339504,"locationURI":"file:\/C:\/Work\/java_work\/Java\/src\/basic\/BooleanExample.java"},{"path":"\/Java\/src\/basic","parentWorkspace":"C:\/Work\/java_work","name":"CastingExample1.java","lastModified":1676860881637,"locationURI":"file:\/C:\/Work\/java_work\/Java\/src\/basic\/CastingExample1.java"},{"path":"\/Java\/src\/basic","parentWorkspace":"C:\/Work\/java_work","name":"VariableExample.java","lastModified":1676857351447,"locationURI":"file:\/C:\/Work\/java_work\/Java\/src\/basic\/VariableExample.java"},{"path":"\/Java\/src\/basic","parentWorkspace":"C:\/Work\/java_work","name":"ScannerExample.java","lastModified":1676879923575,"locationURI":"file:\/C:\/Work\/java_work\/Java\/src\/basic\/ScannerExample.java"},{"path":"\/Java\/src\/basic","parentWorkspace":"C:\/Work\/java_work","name":"TextualExample.java","lastModified":1676859038639,"locationURI":"file:\/C:\/Work\/java_work\/Java\/src\/basic\/TextualExample.java"},{"path":"\/Java\/src\/basic","parentWorkspace":"C:\/Work\/java_work","name":"CastingExample2.java","lastModified":1676862059398,"locationURI":"file:\/C:\/Work\/java_work\/Java\/src\/basic\/CastingExample2.java"},{"path":"\/Java\/src\/basic","parentWorkspace":"C:\/Work\/java_work","name":"IntegerExample.java","lastModified":1676857094875,"locationURI":"file:\/C:\/Work\/java_work\/Java\/src\/basic\/IntegerExample.java"},{"path":"\/Java\/src\/basic","parentWorkspace":"C:\/Work\/java_work","name":"FloatExample.java","lastModified":1676857342605,"locationURI":"file:\/C:\/Work\/java_work\/Java\/src\/basic\/FloatExample.java"},{"path":"\/Java\/src\/basic","parentWorkspace":"C:\/Work\/java_work","name":"ScannerQuiz.java","lastModified":1676880926432,"locationURI":"file:\/C:\/Work\/java_work\/Java\/src\/basic\/ScannerQuiz.java"},{"path":"\/Java\/src\/basic","parentWorkspace":"C:\/Work\/java_work","name":"AssignmentOperator.java","lastModified":1676866391376,"locationURI":"file:\/C:\/Work\/java_work\/Java\/src\/basic\/AssignmentOperator.java"},{"path":"\/Java\/src\/basic","parentWorkspace":"C:\/Work\/java_work","name":"CommentsExample.java","lastModified":1676857353771,"locationURI":"file:\/C:\/Work\/java_work\/Java\/src\/basic\/CommentsExample.java"},{"path":"\/Java\/src\/basic","parentWorkspace":"C:\/Work\/java_work","name":"Hello.java","lastModified":1676857358972,"locationURI":"file:\/C:\/Work\/java_work\/Java\/src\/basic\/Hello.java"},{"path":"\/Java\/src\/basic","parentWorkspace":"C:\/Work\/java_work","name":"Identifier.java","lastModified":1676857348134,"locationURI":"file:\/C:\/Work\/java_work\/Java\/src\/basic\/Identifier.java"},{"path":"\/Java\/src\/basic","parentWorkspace":"C:\/Work\/java_work","name":"PlusMinusOperator.java","lastModified":1676869349424,"locationURI":"file:\/C:\/Work\/java_work\/Java\/src\/basic\/PlusMinusOperator.java"},{"path":"\/Java\/src\/basic","parentWorkspace":"C:\/Work\/java_work","name":"PrintExample.java","lastModified":1676876607655,"locationURI":"file:\/C:\/Work\/java_work\/Java\/src\/basic\/PrintExample.java"},{"path":"\/Java\/src\/basic","parentWorkspace":"C:\/Work\/java_work","name":"LogicalOperator.java","lastModified":1676874595595,"locationURI":"file:\/C:\/Work\/java_work\/Java\/src\/basic\/LogicalOperator.java"},{"path":"\/Java\/src\/basic","parentWorkspace":"C:\/Work\/java_work","name":"CastingExample3.java","lastModified":1676864087317,"locationURI":"file:\/C:\/Work\/java_work\/Java\/src\/basic\/CastingExample3.java"}]}